setup.py
MLML.egg-info/PKG-INFO
MLML.egg-info/SOURCES.txt
MLML.egg-info/dependency_links.txt
MLML.egg-info/top_level.txt
mlml/__init__.py
mlml/algorithm.py
mlml/logging.py
mlml/loss.py
mlml/model.py