Metadata-Version: 1.1
Name: MLML
Version: 0.0.1
Summary: offers support for a variety of algorithms on memory-limited infrastructure
Home-page: https://github.com/alvinwan/mlml
Author: Alvin Wan
Author-email: hi@alvinwan.com
License: BSD
Download-URL: https://github.com/alvinwan/mlml/archive/0.0.1.zip
Platform: UNKNOWN
Classifier: Topic :: Utilities
Classifier: Intended Audience :: Developers
Classifier: Programming Language :: Python :: 3
Classifier: Topic :: Software Development :: Libraries
